oai_rfsim/__init__.py
oai_rfsim/cli.py
oai_rfsim-0.1.0.dist-info/METADATA
oai_rfsim-0.1.0.dist-info/WHEEL
oai_rfsim-0.1.0.dist-info/entry_points.txt
oai_rfsim-0.1.0.dist-info/top_level.txt
oai_rfsim-0.1.0.dist-info/RECORD
