Metadata-Version: 2.1
Name: oai-rfsim
Version: 0.1.0
Summary: Helper tools to build and run OpenAirInterface gNB/UE in RF simulator mode
Home-page: 
Author: OpenAI Assistant
Classifier: Programming Language :: Python :: 3
Classifier: License :: OSI Approved :: MIT License
Classifier: Operating System :: OS Independent
Requires-Python: >=3.8
